pacifica_dispatcher-0.2.5-py3.8-nspkg.pth
pacifica/dispatcher/__init__.py
pacifica/dispatcher/downloader_runners.py
pacifica/dispatcher/event_handlers.py
pacifica/dispatcher/exceptions.py
pacifica/dispatcher/models.py
pacifica/dispatcher/receiver.py
pacifica/dispatcher/router.py
pacifica/dispatcher/uploader_runners.py
pacifica_dispatcher-0.2.5.dist-info/LICENSE
pacifica_dispatcher-0.2.5.dist-info/METADATA
pacifica_dispatcher-0.2.5.dist-info/WHEEL
pacifica_dispatcher-0.2.5.dist-info/namespace_packages.txt
pacifica_dispatcher-0.2.5.dist-info/top_level.txt
pacifica_dispatcher-0.2.5.dist-info/RECORD
