Metadata-Version: 2.1
Name: pacifica-dispatcher
Version: 0.2.5
Summary: Pacifica Dispatcher
Home-page: https://github.com/pacifica/pacifica-dispatcher/
Author: Mark Borkum
Author-email: mark.borkum@pnnl.gov
License: UNKNOWN
Platform: UNKNOWN
Requires-Dist: celery
Requires-Dist: cherrypy
Requires-Dist: cloudevents-python
Requires-Dist: jsonpath2
Requires-Dist: pacifica-downloader
Requires-Dist: pacifica-namespace
Requires-Dist: pacifica-uploader
Requires-Dist: peewee
